pycounts_tat/__init__.py
pycounts_tat/plotting.py
pycounts_tat/pycounts_tat.py
pycounts_tat-0.1.5.dist-info/LICENSE
pycounts_tat-0.1.5.dist-info/WHEEL
pycounts_tat-0.1.5.dist-info/METADATA
pycounts_tat-0.1.5.dist-info/RECORD
